aiocrypto_prices/__init__.py
aiocrypto_prices/_api_requests.py
aiocrypto_prices/aiocrypto_prices.py
aiocrypto_prices/exceptions.py
aiocrypto_prices-0.0.3.dist-info/DESCRIPTION.rst
aiocrypto_prices-0.0.3.dist-info/METADATA
aiocrypto_prices-0.0.3.dist-info/RECORD
aiocrypto_prices-0.0.3.dist-info/WHEEL
aiocrypto_prices-0.0.3.dist-info/metadata.json
aiocrypto_prices-0.0.3.dist-info/top_level.txt
