Metadata-Version: 2.0
Name: aiocrypto-prices
Version: 0.0.3
Summary: asyncio cryptocurrency prices library
Home-page: UNKNOWN
Author: David Jetelina
Author-email: david@djetelina.cz
License: MIT
Keywords: cryptocurrency finance crypto bitcoin asyncio
Platform: UNKNOWN
Classifier: Development Status :: 3 - Alpha
Classifier: Intended Audience :: Developers
Classifier: Topic :: Software Development :: Libraries
Classifier: Topic :: Software Development :: Libraries :: Python Modules
Classifier: Topic :: Utilities
Classifier: License :: OSI Approved :: MIT License
Classifier: Natural Language :: English
Classifier: Operating System :: OS Independent
Classifier: Programming Language :: Python
Classifier: Programming Language :: Python :: 3 :: Only
Classifier: Programming Language :: Python :: 3.6
Requires-Dist: aiohttp (>=2.3.9)
